pyg_downloader/__init__.py
pyg_downloader/downloader.py
pyg_manager/__init__.py
pyg_manager/manager.py
pygcli/__init__.py
pygcli/cli.py
pyg_downloader-0.0.2.dist-info/LICENSE
pyg_downloader-0.0.2.dist-info/METADATA
pyg_downloader-0.0.2.dist-info/WHEEL
pyg_downloader-0.0.2.dist-info/entry_points.txt
pyg_downloader-0.0.2.dist-info/top_level.txt
pyg_downloader-0.0.2.dist-info/RECORD
