Metadata-Version: 2.1
Name: pyg-downloader
Version: 0.0.2
Summary: python download manager
Home-page: https://github.com/GrayHat12/pyg-downloader
Author: GrayHat12
Author-email: grayhathacks10@gmail.com
Project-URL: Bug Tracker, https://github.com/GrayHat12/pyg-downloader/issues
Keywords: download manager downloader file downloader
Classifier: Programming Language :: Python :: 3
Classifier: License :: OSI Approved :: MIT License
Classifier: Operating System :: OS Independent
Classifier: Development Status :: 3 - Alpha
Classifier: Intended Audience :: Developers
Classifier: Topic :: Software Development
Requires-Python: >=3.6
License-File: LICENSE
Requires-Dist: requests (>=2.28.2)
Provides-Extra: atpbar
Requires-Dist: atpbar (>=1.1.4) ; extra == 'atpbar'
